README.md
setup.py
ldaphelper/__init__.py
ldaphelper/helper.py
ldaphelper/ldapconnector.py
ldaphelper/op.py
ldaphelper/passport.py
ldaphelper/trust_relationships.py
ldaphelper.egg-info/PKG-INFO
ldaphelper.egg-info/SOURCES.txt
ldaphelper.egg-info/dependency_links.txt
ldaphelper.egg-info/top_level.txt