Metadata-Version: 2.1
Name: ldaphelper
Version: 0.2.0
Summary: Wanna make ldap handling a little easier
Home-page: https://github.com/christian-hawk/ldaphelper
Author: Christian Eland
Author-email: eland.christian@gmail.com
License: UNKNOWN
Platform: UNKNOWN
Classifier: Programming Language :: Python :: 3
Classifier: License :: OSI Approved :: MIT License
Classifier: Operating System :: OS Independent
Requires-Python: >=3.6
